dephell_archive-0.1.7.dist-info/dependency_links.txt
dephell_archive-0.1.7.dist-info/entry_points.txt
dephell_archive-0.1.7.dist-info/METADATA
dephell_archive-0.1.7.dist-info/top_level.txt
dephell_archive-0.1.7.dist-info/WHEEL
dephell_archive/_glob.py
dephell_archive/_cached_property.py
dephell_archive/_stream.py
dephell_archive/__init__.py
dephell_archive/_path.py
dephell_archive-0.1.7.dist-info/LICENSE
dephell_archive-0.1.7.dist-info/RECORD