Metadata-Version: 2.1
Name: dephell-archive
Version: 0.1.7
Summary: pathlib for archives
Project-URL: Repository, https://github.com/dephell/dephell_archive
Author: Gram
Author-email: gram@orsinium.dev
License: MIT
Requires-Python: >=3.6
Keywords: dephell,pathlib,archive,tar,zip,wheel,sdist
Classifier: Development Status :: 4 - Beta
Classifier: Environment :: Console
Classifier: Intended Audience :: Developers
Classifier: License :: OSI Approved :: MIT License
Classifier: Programming Language :: Python
Classifier: Topic :: Software Development :: Libraries :: Python Modules
Classifier: Topic :: System :: Archiving :: Packaging
Classifier: Topic :: System :: Archiving
Classifier: Topic :: System :: Filesystems
Classifier: Programming Language :: Python :: 3.5
Classifier: Programming Language :: Python :: 3.6
Classifier: Programming Language :: Python :: 3.7
Classifier: Programming Language :: Python :: 3.8
Classifier: Programming Language :: Python :: Implementation :: CPython
Classifier: Programming Language :: Python :: Implementation :: PyPy
Classifier: Operating System :: MacOS
Classifier: Operating System :: Microsoft :: Windows
Classifier: Operating System :: Unix
Requires-Dist: attrs
